witch_ver/__init__.py
witch_ver/_version.py
witch_ver/git.py
witch_ver/integration.py
witch_ver/runner.py
witch_ver/semver.py
witch_ver/version.py
witch_ver/version_hook.py
witch_ver-0.5.2.dist-info/LICENSE
witch_ver-0.5.2.dist-info/METADATA
witch_ver-0.5.2.dist-info/WHEEL
witch_ver-0.5.2.dist-info/entry_points.txt
witch_ver-0.5.2.dist-info/top_level.txt
witch_ver-0.5.2.dist-info/RECORD
