Metadata-Version: 2.1
Name: witch-ver
Version: 0.5.2
Summary: git tag based versioning
Home-page: https://github.com/WattsUp/witch-ver
Author: Bradley Davis
Author-email: me@bradleydavis.tech
License: MIT
Classifier: Programming Language :: Python :: 3
Classifier: Operating System :: OS Independent
Classifier: Development Status :: 4 - Beta
Classifier: License :: OSI Approved :: MIT License
Classifier: Intended Audience :: Developers
Classifier: Topic :: Software Development :: Libraries
Classifier: Programming Language :: Python :: 3
Classifier: Programming Language :: Python :: 3.7
Classifier: Programming Language :: Python :: 3.8
Classifier: Programming Language :: Python :: 3.9
Classifier: Programming Language :: Python :: 3.10
Requires-Python: >=3.7
License-File: LICENSE
Requires-Dist: colorama
Requires-Dist: setuptools
Provides-Extra: dev
Requires-Dist: AutoDict ; extra == 'dev'
Requires-Dist: coverage ; extra == 'dev'
Requires-Dist: time-machine ; extra == 'dev'
Requires-Dist: tomli ; extra == 'dev'
Requires-Dist: ruff ; extra == 'dev'
Requires-Dist: codespell ; extra == 'dev'
Requires-Dist: black ; extra == 'dev'
Requires-Dist: isort ; extra == 'dev'
Requires-Dist: pre-commit ; extra == 'dev'
Provides-Extra: test
Requires-Dist: AutoDict ; extra == 'test'
Requires-Dist: coverage ; extra == 'test'
Requires-Dist: time-machine ; extra == 'test'
Requires-Dist: tomli ; extra == 'test'
